currency_converter_free/__init__.py
currency_converter_free/converter.py
tests/__init__.py
tests/test_converter.py
currency_converter_free-1.0.9.dist-info/LICENSE
currency_converter_free-1.0.9.dist-info/METADATA
currency_converter_free-1.0.9.dist-info/WHEEL
currency_converter_free-1.0.9.dist-info/top_level.txt
currency_converter_free-1.0.9.dist-info/RECORD
