Metadata-Version: 2.1
Name: currency-converter-free
Version: 1.0.9
Summary: A robust and free currency converter module for Python, supporting multiple sources like ECB and CBR.
Home-page: https://github.com/markolofsen/currency-converter-free
Author: Unrealos Team
Author-email: m@unrealos.com
Project-URL: Documentation, https://github.com/markolofsen/currency-converter-free#readme
Project-URL: Bug Tracker, https://github.com/markolofsen/currency-converter-free/issues
Project-URL: Source Code, https://github.com/markolofsen/currency-converter-free
Project-URL: Changelog, https://github.com/markolofsen/currency-converter-free/releases
Keywords: currency converter,python currency API,free currency rates,CBR,ECB,foreign exchange,money conversion
Classifier: Development Status :: 5 - Production/Stable
Classifier: Intended Audience :: Developers
Classifier: License :: OSI Approved :: MIT License
Classifier: Operating System :: OS Independent
Classifier: Programming Language :: Python :: 3
Classifier: Programming Language :: Python :: 3.7
Classifier: Programming Language :: Python :: 3.8
Classifier: Programming Language :: Python :: 3.9
Classifier: Programming Language :: Python :: 3.10
Classifier: Topic :: Software Development :: Libraries
Classifier: Topic :: Office/Business :: Financial :: Accounting
Classifier: Topic :: Utilities
Requires-Python: >=3.7
License-File: LICENSE
Requires-Dist: requests>=2.25
Requires-Dist: diskcache>=5.4
Requires-Dist: cachetools>=5.0
Provides-Extra: dev
Requires-Dist: pytest>=7.0; extra == "dev"
Requires-Dist: unittest; extra == "dev"
Requires-Dist: flake8; extra == "dev"
Requires-Dist: black; extra == "dev"
Requires-Dist: isort; extra == "dev"
Requires-Dist: mypy; extra == "dev"
